celery/__init__.py
celery/__main__.py
celery/_state.py
celery/beat.py
celery/bootsteps.py
celery/canvas.py
celery/datastructures.py
celery/exceptions.py
celery/five.py
celery/local.py
celery/platforms.py
celery/result.py
celery/schedules.py
celery/signals.py
celery/states.py
celery/app/__init__.py
celery/app/amqp.py
celery/app/annotations.py
celery/app/base.py
celery/app/builtins.py
celery/app/control.py
celery/app/defaults.py
celery/app/log.py
celery/app/registry.py
celery/app/routes.py
celery/app/task.py
celery/app/trace.py
celery/app/utils.py
celery/apps/__init__.py
celery/apps/beat.py
celery/apps/worker.py
celery/backends/__init__.py
celery/backends/amqp.py
celery/backends/base.py
celery/backends/cache.py
celery/backends/cassandra.py
celery/backends/couchbase.py
celery/backends/mongodb.py
celery/backends/redis.py
celery/backends/rpc.py
celery/backends/database/__init__.py
celery/backends/database/models.py
celery/backends/database/session.py
celery/bin/__init__.py
celery/bin/amqp.py
celery/bin/base.py
celery/bin/beat.py
celery/bin/celery.py
celery/bin/celeryd_detach.py
celery/bin/events.py
celery/bin/graph.py
celery/bin/multi.py
celery/bin/worker.py
celery/concurrency/__init__.py
celery/concurrency/asynpool.py
celery/concurrency/base.py
celery/concurrency/eventlet.py
celery/concurrency/gevent.py
celery/concurrency/prefork.py
celery/concurrency/solo.py
celery/concurrency/threads.py
celery/contrib/__init__.py
celery/contrib/abortable.py
celery/contrib/batches.py
celery/contrib/methods.py
celery/contrib/migrate.py
celery/contrib/rdb.py
celery/contrib/sphinx.py
celery/events/__init__.py
celery/events/cursesmon.py
celery/events/dumper.py
celery/events/snapshot.py
celery/events/state.py
celery/fixups/__init__.py
celery/fixups/django.py
celery/loaders/__init__.py
celery/loaders/app.py
celery/loaders/base.py
celery/loaders/default.py
celery/security/__init__.py
celery/security/certificate.py
celery/security/key.py
celery/security/serialization.py
celery_3-3.1.26.post4.dist-info/LICENSE
celery_3-3.1.26.post4.dist-info/METADATA
celery_3-3.1.26.post4.dist-info/WHEEL
celery_3-3.1.26.post4.dist-info/entry_points.txt
celery_3-3.1.26.post4.dist-info/top_level.txt
celery_3-3.1.26.post4.dist-info/RECORD
