Metadata-Version: 2.1
Name: celery-3
Version: 3.1.26-4
Summary: Distributed Task Queue
Home-page: http://celeryproject.org
Author: Ask Solem
Author-email: ask@celeryproject.org
License: BSD
Platform: any
Classifier: Development Status :: 5 - Production/Stable
Classifier: License :: OSI Approved :: BSD License
Classifier: Topic :: System :: Distributed Computing
Classifier: Topic :: Software Development :: Object Brokering
Classifier: Programming Language :: Python
Classifier: Programming Language :: Python :: 2
Classifier: Programming Language :: Python :: 2.6
Classifier: Programming Language :: Python :: 2.7
Classifier: Programming Language :: Python :: 3
Classifier: Programming Language :: Python :: 3.3
Classifier: Programming Language :: Python :: 3.4
Classifier: Programming Language :: Python :: Implementation :: CPython
Classifier: Programming Language :: Python :: Implementation :: PyPy
Classifier: Programming Language :: Python :: Implementation :: Jython
Classifier: Operating System :: OS Independent
Classifier: Operating System :: POSIX
Classifier: Operating System :: Microsoft :: Windows
Classifier: Operating System :: MacOS :: MacOS X
Requires-Dist: pytz (>dev)
Requires-Dist: billiard (<3.4,>=3.3.0.23)
Requires-Dist: kombu (<3.1,>=3.0.37)
Provides-Extra: auth
Requires-Dist: pyOpenSSL ; extra == 'auth'
Provides-Extra: beanstalk
Requires-Dist: beanstalkc ; extra == 'beanstalk'
Provides-Extra: cassandra
Requires-Dist: pycassa ; extra == 'cassandra'
Provides-Extra: couchbase
Requires-Dist: couchbase ; extra == 'couchbase'
Provides-Extra: couchdb
Requires-Dist: couchdb ; extra == 'couchdb'
Provides-Extra: eventlet
Requires-Dist: eventlet ; extra == 'eventlet'
Provides-Extra: gevent
Requires-Dist: gevent ; extra == 'gevent'
Provides-Extra: librabbitmq
Requires-Dist: librabbitmq (>=1.6.1) ; extra == 'librabbitmq'
Provides-Extra: memcache
Requires-Dist: pylibmc ; extra == 'memcache'
Provides-Extra: mongodb
Requires-Dist: pymongo (>=2.6.2) ; extra == 'mongodb'
Provides-Extra: msgpack
Requires-Dist: msgpack-python (>=0.3.0) ; extra == 'msgpack'
Provides-Extra: pyro
Requires-Dist: pyro4 ; extra == 'pyro'
Provides-Extra: redis
Requires-Dist: redis (<3.0.0,>=2.8.0) ; extra == 'redis'
Provides-Extra: slmq
Requires-Dist: softlayer-messaging (>=1.0.3) ; extra == 'slmq'
Provides-Extra: sqlalchemy
Requires-Dist: sqlalchemy ; extra == 'sqlalchemy'
Provides-Extra: sqs
Requires-Dist: boto (>=2.13.3) ; extra == 'sqs'
Provides-Extra: threads
Requires-Dist: threadpool ; extra == 'threads'
Provides-Extra: yaml
Requires-Dist: PyYAML (>=3.10) ; extra == 'yaml'
Provides-Extra: zeromq
Requires-Dist: pyzmq (>=13.1.0) ; extra == 'zeromq'
Provides-Extra: zookeeper
Requires-Dist: kazoo (>=1.3.1) ; extra == 'zookeeper'
